{
  "enabled": true,
  "disabled_ecosystems": [],
  "reason": "",
  "incident_url": "",
  "disabled_by": "",
  "disabled_at": "",
  "expected_resume": "",
  "circuit_breaker": {
    "github": {
      "state": "open",
      "failures": 299,
      "last_failure": "2026-04-04T13:57:24Z",
      "opens_at": "2026-04-04T14:57:24Z"
    },
    "homebrew": {
      "state": "open",
      "failures": 260,
      "last_failure": "2026-04-04T13:57:24Z",
      "opens_at": "2026-04-04T14:57:24Z"
    },
    "rubygems": {
      "state": "open",
      "failures": 195,
      "last_failure": "2026-04-04T13:57:24Z",
      "opens_at": "2026-04-04T14:57:24Z"
    },
    "crates.io": {
      "state": "open",
      "failures": 296,
      "last_failure": "2026-04-04T13:57:24Z",
      "opens_at": "2026-04-04T14:57:24Z"
    },
    "npm": {
      "state": "closed",
      "failures": 1,
      "last_failure": "2026-04-04T13:57:24Z",
      "opens_at": "2026-03-27T19:57:33Z"
    },
    "pypi": {
      "state": "open",
      "failures": 276,
      "last_failure": "2026-03-27T20:44:43Z",
      "opens_at": "2026-03-27T21:44:43Z"
    },
    "default": {
      "state": "closed",
      "failures": 0
    }
  },
  "budget": {
    "macos_minutes_used": 0,
    "linux_minutes_used": 0,
    "week_start": "",
    "sampling_active": false
  }
}
