{
  "enabled": true,
  "disabled_ecosystems": [],
  "reason": "",
  "incident_url": "",
  "disabled_by": "",
  "disabled_at": "",
  "expected_resume": "",
  "circuit_breaker": {
    "github": {
      "state": "open",
      "failures": 39,
      "last_failure": "2026-03-03T04:41:23Z",
      "opens_at": "2026-03-03T05:41:23Z"
    },
    "homebrew": {
      "state": "closed",
      "failures": 0,
      "last_failure": "2026-03-03T04:17:57Z",
      "opens_at": "2026-03-02T19:46:21Z"
    },
    "rubygems": {
      "state": "open",
      "failures": 39,
      "last_failure": "2026-03-02T19:40:14Z",
      "opens_at": "2026-03-02T20:40:14Z"
    },
    "crates.io": {
      "state": "open",
      "failures": 39,
      "last_failure": "2026-03-02T19:40:14Z",
      "opens_at": "2026-03-02T20:40:14Z"
    },
    "npm": {
      "state": "open",
      "failures": 39,
      "last_failure": "2026-03-02T19:40:14Z",
      "opens_at": "2026-03-02T20:40:14Z"
    },
    "pypi": {
      "state": "open",
      "failures": 36,
      "last_failure": "2026-03-02T19:40:14Z",
      "opens_at": "2026-03-02T20:40:14Z"
    }
  },
  "budget": {
    "macos_minutes_used": 0,
    "linux_minutes_used": 0,
    "week_start": "",
    "sampling_active": false
  }
}
