{
  "enabled": true,
  "disabled_ecosystems": [],
  "reason": "",
  "incident_url": "",
  "disabled_by": "",
  "disabled_at": "",
  "expected_resume": "",
  "circuit_breaker": {
    "github": {
      "state": "open",
      "failures": 402,
      "last_failure": "2026-04-20T10:51:13Z",
      "opens_at": "2026-04-20T11:51:13Z"
    },
    "homebrew": {
      "state": "open",
      "failures": 363,
      "last_failure": "2026-04-20T10:51:13Z",
      "opens_at": "2026-04-20T11:51:13Z"
    },
    "rubygems": {
      "state": "open",
      "failures": 40,
      "last_failure": "2026-04-20T10:51:13Z",
      "opens_at": "2026-04-20T11:51:13Z"
    },
    "crates.io": {
      "state": "open",
      "failures": 399,
      "last_failure": "2026-04-20T10:51:13Z",
      "opens_at": "2026-04-20T11:51:13Z"
    },
    "npm": {
      "state": "open",
      "failures": 103,
      "last_failure": "2026-04-20T10:51:13Z",
      "opens_at": "2026-04-20T11:51:13Z"
    },
    "pypi": {
      "state": "open",
      "failures": 372,
      "last_failure": "2026-04-20T10:51:13Z",
      "opens_at": "2026-04-20T11:51:13Z"
    },
    "default": {
      "state": "closed",
      "failures": 0
    }
  },
  "budget": {
    "macos_minutes_used": 0,
    "linux_minutes_used": 0,
    "week_start": "",
    "sampling_active": false
  }
}
