{
  "enabled": true,
  "disabled_ecosystems": [],
  "reason": "",
  "incident_url": "",
  "disabled_by": "",
  "disabled_at": "",
  "expected_resume": "",
  "circuit_breaker": {
    "homebrew": {
      "state": "open",
      "failures": 6,
      "last_failure": "2026-02-21T01:37:19Z",
      "opens_at": "2026-02-21T02:37:19Z"
    },
    "github": {
      "state": "open",
      "failures": 6,
      "last_failure": "2026-02-21T01:37:19Z",
      "opens_at": "2026-02-21T02:37:19Z"
    },
    "crates.io": {
      "state": "open",
      "failures": 6,
      "last_failure": "2026-02-21T01:37:19Z",
      "opens_at": "2026-02-21T02:37:19Z"
    },
    "npm": {
      "state": "open",
      "failures": 6,
      "last_failure": "2026-02-21T01:37:19Z",
      "opens_at": "2026-02-21T02:37:19Z"
    },
    "rubygems": {
      "state": "open",
      "failures": 6,
      "last_failure": "2026-02-21T01:37:19Z",
      "opens_at": "2026-02-21T02:37:19Z"
    },
    "pypi": {
      "state": "open",
      "failures": 6,
      "last_failure": "2026-02-21T01:37:19Z",
      "opens_at": "2026-02-21T02:37:19Z"
    }
  },
  "budget": {
    "macos_minutes_used": 0,
    "linux_minutes_used": 0,
    "week_start": "",
    "sampling_active": false
  }
}
