{
  "enabled": true,
  "disabled_ecosystems": [],
  "reason": "",
  "incident_url": "",
  "disabled_by": "",
  "disabled_at": "",
  "expected_resume": "",
  "circuit_breaker": {
    "github": {
      "state": "open",
      "failures": 413,
      "last_failure": "2026-04-21T09:29:26Z",
      "opens_at": "2026-04-21T10:29:26Z"
    },
    "homebrew": {
      "state": "open",
      "failures": 374,
      "last_failure": "2026-04-21T09:29:26Z",
      "opens_at": "2026-04-21T10:29:26Z"
    },
    "rubygems": {
      "state": "open",
      "failures": 51,
      "last_failure": "2026-04-21T09:29:26Z",
      "opens_at": "2026-04-21T10:29:26Z"
    },
    "crates.io": {
      "state": "open",
      "failures": 410,
      "last_failure": "2026-04-21T09:29:26Z",
      "opens_at": "2026-04-21T10:29:26Z"
    },
    "npm": {
      "state": "open",
      "failures": 114,
      "last_failure": "2026-04-21T09:29:26Z",
      "opens_at": "2026-04-21T10:29:26Z"
    },
    "pypi": {
      "state": "open",
      "failures": 383,
      "last_failure": "2026-04-21T09:29:26Z",
      "opens_at": "2026-04-21T10:29:26Z"
    },
    "default": {
      "state": "closed",
      "failures": 0
    }
  },
  "budget": {
    "macos_minutes_used": 0,
    "linux_minutes_used": 0,
    "week_start": "",
    "sampling_active": false
  }
}
