{
  "enabled": true,
  "disabled_ecosystems": [],
  "reason": "",
  "incident_url": "",
  "disabled_by": "",
  "disabled_at": "",
  "expected_resume": "",
  "circuit_breaker": {
    "github": {
      "state": "open",
      "failures": 508,
      "last_failure": "2026-04-30T06:03:43Z",
      "opens_at": "2026-04-30T07:03:43Z"
    },
    "homebrew": {
      "state": "open",
      "failures": 469,
      "last_failure": "2026-04-30T06:03:43Z",
      "opens_at": "2026-04-30T07:03:43Z"
    },
    "rubygems": {
      "state": "open",
      "failures": 146,
      "last_failure": "2026-04-30T06:03:43Z",
      "opens_at": "2026-04-30T07:03:43Z"
    },
    "crates.io": {
      "state": "open",
      "failures": 505,
      "last_failure": "2026-04-30T06:03:43Z",
      "opens_at": "2026-04-30T07:03:43Z"
    },
    "npm": {
      "state": "open",
      "failures": 209,
      "last_failure": "2026-04-30T06:03:43Z",
      "opens_at": "2026-04-30T07:03:43Z"
    },
    "pypi": {
      "state": "open",
      "failures": 478,
      "last_failure": "2026-04-30T06:03:43Z",
      "opens_at": "2026-04-30T07:03:43Z"
    },
    "default": {
      "state": "closed",
      "failures": 0
    }
  },
  "budget": {
    "macos_minutes_used": 0,
    "linux_minutes_used": 0,
    "week_start": "",
    "sampling_active": false
  }
}
