{
  "tool": "atop",
  "selected": "homebrew:atop",
  "alternatives": [
    "crates.io:atop",
    "pypi:atop"
  ],
  "selection_reason": "priority_fallback",
  "downloads_ratio": 8.515625,
  "high_risk": true,
  "probe_results": [
    {
      "source": "homebrew:atop",
      "downloads": 545,
      "version_count": 0,
      "has_repository": true
    },
    {
      "source": "pypi:atop",
      "downloads": 0,
      "version_count": 14,
      "has_repository": true
    },
    {
      "source": "crates.io:atop",
      "downloads": 64,
      "version_count": 5,
      "has_repository": false
    },
    {
      "source": "npm:atop",
      "downloads": 0,
      "version_count": 1,
      "has_repository": false
    }
  ],
  "previous_source": "homebrew:atop",
  "disambiguated_at": "2026-02-17T00:11:13.517000322Z",
  "seeding_run": "2026-02-17T00:10:01.867521792Z"
}
