{
  "tool": "hysteria",
  "selected": "rubygems:hysteria",
  "alternatives": [
    "homebrew:hysteria",
    "pypi:hysteria"
  ],
  "selection_reason": "priority_fallback",
  "downloads_ratio": 4.668946648426813,
  "high_risk": true,
  "probe_results": [
    {
      "source": "homebrew:hysteria",
      "downloads": 731,
      "version_count": 0,
      "has_repository": true
    },
    {
      "source": "pypi:hysteria",
      "downloads": 0,
      "version_count": 3,
      "has_repository": true
    },
    {
      "source": "rubygems:hysteria",
      "downloads": 3413,
      "version_count": 1,
      "has_repository": false
    },
    {
      "source": "npm:hysteria",
      "downloads": 0,
      "version_count": 1,
      "has_repository": true
    }
  ],
  "previous_source": "homebrew:hysteria",
  "disambiguated_at": "2026-02-17T00:18:32.448449904Z",
  "seeding_run": "2026-02-17T00:10:01.867521792Z"
}
