{
  "tool": "imageoptim-cli",
  "selected": "npm:imageoptim-cli",
  "alternatives": [
    "homebrew:imageoptim-cli"
  ],
  "selection_reason": "priority_fallback",
  "downloads_ratio": 4.215801886792453,
  "high_risk": true,
  "probe_results": [
    {
      "source": "homebrew:imageoptim-cli",
      "downloads": 848,
      "version_count": 0,
      "has_repository": true
    },
    {
      "source": "npm:imageoptim-cli",
      "downloads": 3575,
      "version_count": 49,
      "has_repository": true
    }
  ],
  "previous_source": "homebrew:imageoptim-cli",
  "disambiguated_at": "2026-02-17T00:18:43.487253389Z",
  "seeding_run": "2026-02-17T00:10:01.867521792Z"
}
