{
  "tool": "rbspy",
  "selected": "crates.io:rbspy",
  "alternatives": [
    "homebrew:rbspy"
  ],
  "selection_reason": "priority_fallback",
  "downloads_ratio": 1.9384541984732824,
  "high_risk": true,
  "probe_results": [
    {
      "source": "homebrew:rbspy",
      "downloads": 2096,
      "version_count": 0,
      "has_repository": true
    },
    {
      "source": "crates.io:rbspy",
      "downloads": 4063,
      "version_count": 62,
      "has_repository": true
    }
  ],
  "previous_source": "homebrew:rbspy",
  "disambiguated_at": "2026-02-17T00:26:40.365136828Z",
  "seeding_run": "2026-02-17T00:10:01.867521792Z"
}
